lazyfields/__init__.py
lazyfields/_lazyfields.py
lazy_fields-1.1.2.dist-info/LICENSE
lazy_fields-1.1.2.dist-info/METADATA
lazy_fields-1.1.2.dist-info/WHEEL
lazy_fields-1.1.2.dist-info/RECORD
