Metadata-Version: 2.1
Name: lazy-fields
Version: 1.1.2
Summary: Lazy attributes to delay initialization
Author: Gustavo Cardoso
Author-email: self.gustavocorrea@gmail.com
Requires-Python: >=3.9,<4.0
Classifier: Programming Language :: Python :: 3
Classifier: Programming Language :: Python :: 3.9
Classifier: Programming Language :: Python :: 3.10
Classifier: Programming Language :: Python :: 3.11
Classifier: Programming Language :: Python :: 3.12
Classifier: Programming Language :: Python :: 3.13
Requires-Dist: typing-extensions (>=4.7.1,<5.0.0) ; python_full_version > "3.0.0" and python_version < "3.11"
